eridaspeed/__init__.py
eridaspeed/optimizer.py
eridaspeed-0.1.0.dist-info/METADATA
eridaspeed-0.1.0.dist-info/WHEEL
eridaspeed-0.1.0.dist-info/top_level.txt
eridaspeed-0.1.0.dist-info/RECORD
